{
  "hash": "00ce6995",
  "configHash": "1331ba0a",
  "lockfileHash": "08e65da9",
  "browserHash": "f7ac5742",
  "optimized": {
    "vue": {
      "src": "../../../node_modules/vue/dist/vue.runtime.esm-bundler.js",
      "file": "vue.js",
      "fileHash": "c40ca6c6",
      "needsInterop": false
    },
    "vitepress > @vue/devtools-api": {
      "src": "../../../node_modules/@vue/devtools-api/dist/index.js",
      "file": "vitepress___@vue_devtools-api.js",
      "fileHash": "01c9548e",
      "needsInterop": false
    },
    "vitepress > @vueuse/core": {
      "src": "../../../node_modules/@vueuse/core/index.mjs",
      "file": "vitepress___@vueuse_core.js",
      "fileHash": "051eff7b",
      "needsInterop": false
    },
    "@braintree/sanitize-url": {
      "src": "../../../node_modules/@braintree/sanitize-url/dist/index.js",
      "file": "@braintree_sanitize-url.js",
      "fileHash": "c6271cf7",
      "needsInterop": true
    },
    "dayjs": {
      "src": "../../../node_modules/dayjs/dayjs.min.js",
      "file": "dayjs.js",
      "fileHash": "75a0ee17",
      "needsInterop": true
    },
    "cytoscape-cose-bilkent": {
      "src": "../../../node_modules/cytoscape-cose-bilkent/cytoscape-cose-bilkent.js",
      "file": "cytoscape-cose-bilkent.js",
      "fileHash": "6c2d46dd",
      "needsInterop": true
    },
    "cytoscape": {
      "src": "../../../node_modules/cytoscape/dist/cytoscape.esm.mjs",
      "file": "cytoscape.js",
      "fileHash": "b6d6275d",
      "needsInterop": false
    }
  },
  "chunks": {
    "chunk-P622L5TS": {
      "file": "chunk-P622L5TS.js"
    },
    "chunk-BUSYA2B4": {
      "file": "chunk-BUSYA2B4.js"
    }
  }
}